utfuzz/.dmypy.json
utfuzz/.utfuzz.log
utfuzz/__init__.py
utfuzz/__main__.py
utfuzz/config/__init__.py
utfuzz/config/config.py
utfuzz/config/config_manager.py
utfuzz/exceptions/__init__.py
utfuzz/exceptions/exceptions.py
utfuzz/file_manager/__init__.py
utfuzz/file_manager/directory_manager.py
utfuzz/file_manager/file_finder.py
utfuzz/file_manager/relative_path.py
utfuzz/main.py
utfuzz/parser.py
utfuzz/requirements_managers/__init__.py
utfuzz/requirements_managers/java_requirements_manager.py
utfuzz/requirements_managers/python_requirements_manger.py
utfuzz/user_interface/__init__.py
utfuzz/user_interface/printer.py
utfuzz/user_interface/reader.py
utfuzz/user_interface/utils.py
utfuzz/utbot-cli-python.jar
utfuzz/utbot_manager/__init__.py
utfuzz/utbot_manager/utbot_loader.py
utfuzz/utbot_manager/utbot_manager.py
utfuzz/utfuzz_config.json
utfuzz-0.1.14.dist-info/METADATA
utfuzz-0.1.14.dist-info/WHEEL
utfuzz-0.1.14.dist-info/entry_points.txt
utfuzz-0.1.14.dist-info/RECORD
