Metadata-Version: 2.1
Name: utfuzz
Version: 0.1.14
Summary: 
Author: Vyacheslav Tamarin
Author-email: tamarin.vs@ya.ru
Requires-Python: >=3.9,<4.0
Classifier: Programming Language :: Python :: 3
Classifier: Programming Language :: Python :: 3.9
Classifier: Programming Language :: Python :: 3.10
Classifier: Programming Language :: Python :: 3.11
Requires-Dist: install-jdk (>=1.1.0,<2.0.0)
Requires-Dist: tqdm (>=4.66.1,<5.0.0)
